mseep_litserve-1.0.0.dist-info/licenses/LICENSE
tests/__init__.py
tests/conftest.py
tests/minimal_run.py
tests/simple_server.py
tests/simple_server_diff_port.py
mseep_litserve-1.0.0.dist-info/METADATA
mseep_litserve-1.0.0.dist-info/WHEEL
mseep_litserve-1.0.0.dist-info/top_level.txt
mseep_litserve-1.0.0.dist-info/RECORD
